cglearnlatest/CKES_discrete.py
cglearnlatest/CKES_gaussian.py
cglearnlatest/__init__.py
cglearnlatest/ancestralset.py
cglearnlatest/as_freq_tb.py
cglearnlatest/calculate_deviance.py
cglearnlatest/comp_freq_tb.dll
cglearnlatest/comp_freq_tb.so
cglearnlatest/comp_pat.py
cglearnlatest/comp_skel.py
cglearnlatest/compress_freq_table.py
cglearnlatest/cond_ind_test.dll
cglearnlatest/cond_ind_test.so
cglearnlatest/draw.py
cglearnlatest/freq_table.py
cglearnlatest/gaussian_skeleton_mkb.py
cglearnlatest/gaussianpclearn.py
cglearnlatest/get_multinom_dist.py
cglearnlatest/get_normal_dist.py
cglearnlatest/get_toy_graph_discrete.py
cglearnlatest/get_toy_graph_gaussian.py
cglearnlatest/graph.py
cglearnlatest/helper.py
cglearnlatest/inducedsubgraph.py
cglearnlatest/is_chain_graph.py
cglearnlatest/ischaingraph.py
cglearnlatest/isseparated.py
cglearnlatest/istriangulated.py
cglearnlatest/junctiontree.py
cglearnlatest/learn_complex_multinom.py
cglearnlatest/learn_complex_norm.py
cglearnlatest/learn_skeleton_multinom.py
cglearnlatest/learn_skeleton_norm.py
cglearnlatest/mbcsp_discrete.py
cglearnlatest/mbcsp_gaussian.py
cglearnlatest/moralize.py
cglearnlatest/multinom_ci_test.py
cglearnlatest/multinom_pc_learn.py
cglearnlatest/multinom_skeleton_mkb.py
cglearnlatest/norm_ci_test.py
cglearnlatest/pattern.py
cglearnlatest/rmultinom_cg.py
cglearnlatest/rnorm_cg.py
cglearnlatest/skeleton.py
cglearnlatest/toyMulti.csv
cglearnlatest/toygraph.csv
cglearnlatest/triangulate.py
cglearnlatest/ugtojtree.py
cglearnlatest/uig_multinom.py
cglearnlatest/uig_norm.py
cglearnlatest/binaries/__init__.py
cglearnlatest/binaries/comp_freq_tb.dll
cglearnlatest/binaries/comp_freq_tb.so
cglearnlatest/binaries/cond_ind_test.dll
cglearnlatest/binaries/cond_ind_test.so
cglearnlatest/data/__init__.py
cglearnlatest/data/toyMulti.csv
cglearnlatest/data/toygraph.csv
cglearnlatest-0.6.dist-info/LICENSE
cglearnlatest-0.6.dist-info/METADATA
cglearnlatest-0.6.dist-info/WHEEL
cglearnlatest-0.6.dist-info/top_level.txt
cglearnlatest-0.6.dist-info/RECORD
