Metadata-Version: 2.1
Name: cglearnlatest
Version: 0.6
Summary: Description of your package
Home-page: https://github.com
Author: shantanu
Author-email: ssppdd18@gmail.com
Classifier: Programming Language :: Python :: 3
Classifier: License :: OSI Approved :: MIT License
Classifier: Operating System :: OS Independent
Requires-Python: >=3.6
License-File: LICENSE
Requires-Dist: numpy
Requires-Dist: networkx
Requires-Dist: matplotlib
Requires-Dist: pandas
Requires-Dist: igraph
Requires-Dist: scipy
Provides-Extra: extras
